jasmine/__init__.py
jasmine/jasmine.py
jasmine_rice-0.1.0.dist-info/licenses/LICENSE
jasmine_rice-0.1.0.dist-info/METADATA
jasmine_rice-0.1.0.dist-info/WHEEL
jasmine_rice-0.1.0.dist-info/entry_points.txt
jasmine_rice-0.1.0.dist-info/top_level.txt
jasmine_rice-0.1.0.dist-info/RECORD
