Metadata-Version: 2.4
Name: jasmine-rice
Version: 0.1.0
Summary: Just A Simple Manager for Incredibly Nice Environments
Author: Anonymous
License: MIT
Requires-Python: >=3.10
License-File: LICENSE
Requires-Dist: toml
Dynamic: license-file
